{
	"id": "60ecf5ec-eb74-4a9a-8dce-3526ca859ed1",
	"name": "MV Sense",
	"values": [
		{
			"key": "baseUrl",
			"value": "https://api.meraki.com/api/v0",
			"enabled": true
		},
		{
			"key": "serial",
			"value": "Q2FV-TG7N-MF4E",
			"enabled": true
		},
		{
			"key": "X-Cisco-Meraki-API-Key",
			"value": "6bec40cf957de430a6f1f2baa056b99a4fac9ea0",
			"enabled": true
		},
		{
			"key": "organizationId",
			"value": "549236",
			"enabled": true
		},
		{
			"key": "networkId",
			"value": "",
			"enabled": true
		},
		{
			"key": "zoneID",
			"value": "0",
			"enabled": true
		}
	],
	"_postman_variable_scope": "environment",
	"_postman_exported_at": "2019-05-28T04:58:53.452Z",
	"_postman_exported_using": "Postman/7.0.9"
}